whisper_lm_transformers/__init__.py
whisper_lm_transformers/logits_processor.py
whisper_lm_transformers/whisper_with_lm.py
whisper_lm_transformers/whisper_with_lm_pipeline.py
whisper_lm_transformers/scripts/__init__.py
whisper_lm_transformers/scripts/whisper_evaluate_with_hf.py
whisper_lm_transformers/scripts/whisper_lm_optimizer_with_hf.py
whisper_lm_transformers-0.2.0.dist-info/licenses/LICENSE
whisper_lm_transformers-0.2.0.dist-info/METADATA
whisper_lm_transformers-0.2.0.dist-info/WHEEL
whisper_lm_transformers-0.2.0.dist-info/entry_points.txt
whisper_lm_transformers-0.2.0.dist-info/top_level.txt
whisper_lm_transformers-0.2.0.dist-info/RECORD
