Metadata-Version: 2.4
Name: whisper-lm-transformers
Version: 0.2.0
Summary: Add language model support to HF Transformers' Whisper models
Author-email: Xabier de Zuazo <xabier@zuazo.org>
License: 
Project-URL: Homepage, https://github.com/hitz-zentroa/whisper-lm-transformers
Project-URL: Source, https://github.com/hitz-zentroa/whisper-lm-transformers
Keywords: whisper,kenlm,llm,transformers,speech-recognition
Classifier: Programming Language :: Python :: 3
Classifier: License :: OSI Approved :: Apache Software License
Classifier: Operating System :: OS Independent
Requires-Python: >=3.8
License-File: LICENSE
Requires-Dist: datasets
Requires-Dist: evaluate
Requires-Dist: jiwer
Requires-Dist: librosa
Requires-Dist: optuna>=4.1.0
Requires-Dist: openai-whisper
Requires-Dist: tabulate
Requires-Dist: transformers>=4.31.0
Provides-Extra: dev
Requires-Dist: autoflake==2.3.1; extra == "dev"
Requires-Dist: bandit==1.8.3; extra == "dev"
Requires-Dist: black==25.1.0; extra == "dev"
Requires-Dist: blacken-docs==1.19.1; extra == "dev"
Requires-Dist: flake8==7.1.2; extra == "dev"
Requires-Dist: isort==6.0.1; extra == "dev"
Requires-Dist: pydocstringformatter==0.7.3; extra == "dev"
Requires-Dist: pylint==3.3.4; extra == "dev"
Requires-Dist: ruff==0.9.10; extra == "dev"
Dynamic: license-file
